[
  {
    "line": "ابَدی بنتا ہے یہ عالمِ فانی جس سے",
    "start": 23,
    "end": 27,
    "line_number": 6,
    "file": 80,
    "first": true,
    "other": "ایک افسانۂ رنگیں ہے جوانی جس سے"
  },
  {
    "line": "عقلِ انسانی ہے فانی، زندۂ جاوید عشق",
    "start": 15,
    "end": 19,
    "line_number": 35,
    "file": 100,
    "first": false,
    "other": "ہے ابد کے نسخۂ دیرینہ کی تمہید عشق"
  },
  {
    "line": "مکاں فانی، مکیں آنی، ازل تیرا، ابد تیرا",
    "start": 5,
    "end": 9,
    "line_number": 41,
    "file": 163,
    "first": true,
    "other": "خدا کا آخری پیغام ہے تُو، جاوداں تو ہے"
  },
  {
    "line": "دونوں کے صنم خاکی، دونوں کے صنم فانی",
    "start": 32,
    "end": 36,
    "line_number": 22,
    "file": 229,
    "first": false,
    "other": "تیرے بھی صنم خانے، میرے بھی صنم خانے"
  },
  {
    "line": "آنی و فانی تمام معجزہ ہائے ہُنر",
    "start": 6,
    "end": 10,
    "line_number": 15,
    "file": 317,
    "first": true,
    "other": "کارِ جہاں بےثبات، کارِ جہاں بےثبات!"
  },
  {
    "line": "اُسے خبر ہے، یہ باقی ہے اور وہ فانی",
    "start": 31,
    "end": 35,
    "line_number": 10,
    "file": 437,
    "first": false,
    "other": "وجود صیرفیِ کائنات ہے اُس کا"
  },
  {
    "line": "حُسنِ تدبیر سے دے آنی و فانی کو ثبات",
    "start": 24,
    "end": 28,
    "line_number": 6,
    "file": 640,
    "first": false,
    "other": "مجھ سے فرمایا کہ لے، اور شہنشاہی کر"
  }
]