[
  {
    "before": "یہ تو",
    "word": "حُجّت",
    "after": "ہے ہَوا کی قُوّتِ تعمیر پر",
    "line": 107,
    "file": 140,
    "first": false,
    "other": "اس روِش کا کیا اثر ہے ہیئتِ تعمیر پر"
  },
  {
    "before": "میرے کلام پہ",
    "word": "حجت",
    "after": "ہے نکتۂ لولاک",
    "line": 22,
    "file": 277,
    "first": false,
    "other": "جہاں تمام ہے میراث مردِ مومن کی"
  },
  {
    "before": "پستیِ فطرت نے سِکھلائی ہے یہ",
    "word": "حُجتّ",
    "after": "اسے",
    "line": 17,
    "file": 433,
    "first": true,
    "other": "کہتا ہے ’تیری مشیّت میں نہ تھا میرا سجود،"
  },
  {
    "before": "کس کی نومیدی پہ",
    "word": "حجت",
    "after": "ہے یہ فرمانِ جدید؟",
    "line": 30,
    "file": 598,
    "first": true,
    "other": "’ہے جہاد اس دَور میں مردِ مسلماںپر حرام!"
  }
]