[
  {
    "line": "پردۂ نور میں مستور ہے ہر شے تیری",
    "start": 0,
    "end": 4,
    "line_number": 18,
    "file": 25,
    "first": false,
    "other": "رُتبہ تیرا ہے بڑا، شان بڑی ہے تیری"
  },
  {
    "line": "حُسنِ ازل کہ پردۂ لالہ و گُل میں ہے نہاں",
    "start": 13,
    "end": 17,
    "line_number": 15,
    "file": 76,
    "first": true,
    "other": "کہتے ہیں بےقرار ہے جلوۂ عام کے لیے"
  },
  {
    "line": "پردۂ انگور سے نکلی تو مِیناؤں میں تھی",
    "start": 0,
    "end": 4,
    "line_number": 10,
    "file": 91,
    "first": false,
    "other": "کس قدر اے مے! تجھے رسمِ حجاب آئی پسند"
  },
  {
    "line": "سکُوت تھا پردہ دار جس کا، وہ راز اب آشکار ہو گا",
    "start": 10,
    "end": 14,
    "line_number": 4,
    "file": 93,
    "first": false,
    "other": "زمانہ آیا ہے بےحجابی کا، عام دیدارِ یار ہو گا"
  },
  {
    "line": "پردۂ خدمتِ دیں میں ہوَسِ جاہ کا راز",
    "start": 0,
    "end": 4,
    "line_number": 19,
    "file": 111,
    "first": false,
    "other": "اور لوگوں کی طرح تُو بھی چھُپا سکتا ہے"
  },
  {
    "line": "پردۂ دل میں محبّت کو ابھی مستور رکھ",
    "start": 0,
    "end": 4,
    "line_number": 116,
    "file": 117,
    "first": true,
    "other": "یعنی اپنی مے کو رُسوا صُورتِ مِینا نہ کر"
  },
  {
    "line": "دل کی کیفیّت ہے پیدا پردۂ تقریر میں",
    "start": 21,
    "end": 25,
    "line_number": 162,
    "file": 117,
    "first": true,
    "other": "کِسوتِ مِینا میں مے مستُور بھی، عُریاں بھی ہے"
  },
  {
    "line": "پردہ رکھتا ہے اگر کوئی تمھارا، تو غریب",
    "start": 0,
    "end": 4,
    "line_number": 104,
    "file": 121,
    "first": false,
    "other": "نام لیتا ہے اگر کوئی ہمارا، تو غریب"
  },
  {
    "line": "پردۂ مجبوری و بےچارگی تدبیر ہے",
    "start": 0,
    "end": 4,
    "line_number": 4,
    "file": 140,
    "first": false,
    "other": "ذرّہ ذرّہ دہر کا زندانیِ تقدیر ہے"
  },
  {
    "line": "ہیں پسِ نُہ پردۂ گردُوں ابھی دَور اور بھی",
    "start": 12,
    "end": 16,
    "line_number": 82,
    "file": 140,
    "first": false,
    "other": "ختم ہو جائے گا لیکن امتحاں کا دَور بھی"
  },
  {
    "line": "پردۂ مشرق سے جس دم جلوہ گر ہوتی ہے صبح",
    "start": 0,
    "end": 4,
    "line_number": 159,
    "file": 140,
    "first": true,
    "other": "داغ شب کا دامنِ آفاق سے دھوتی ہے صبح"
  },
  {
    "line": "پردہ چہرے سے اُٹھا، انجمن آرائی کر",
    "start": 0,
    "end": 4,
    "line_number": 3,
    "file": 167,
    "first": true,
    "other": "چشمِ مہر و مہ و انجم کو تماشائی کر"
  },
  {
    "line": "وہ سرود کیا کہ چھُپا ہوا ہو سکوتِ پردۂ ساز میں",
    "start": 34,
    "end": 38,
    "line_number": 7,
    "file": 169,
    "first": false,
    "other": "طرَب آشنائے خروش ہو، تُو نَوا ہے محرمِ گوش ہو"
  },
  {
    "line": "پردہ اُٹھنے کی منتظرِ ہے نگاہ",
    "start": 0,
    "end": 4,
    "line_number": 10,
    "file": 173,
    "first": false,
    "other": "یہ ڈراما دِکھائے گا کیا سِین"
  },
  {
    "line": "کہہ گئیں رازِ محبّت پردہ دارِیہاے شوق",
    "start": 20,
    "end": 24,
    "line_number": 15,
    "file": 227,
    "first": true,
    "other": "تھی فغاں وہ بھی جسے ضبطِ فغاں سمجھا تھا میں"
  },
  {
    "line": "مَیں نے تو کِیا پردۂ اسرار کو بھی چاک",
    "start": 16,
    "end": 20,
    "line_number": 15,
    "file": 243,
    "first": true,
    "other": "دیرینہ ہے تیرا مَرضِ کور نگاہی"
  },
  {
    "line": "حادثہ وہ جو ابھی پردۂ افلاک میں ہے",
    "start": 17,
    "end": 21,
    "line_number": 3,
    "file": 275,
    "first": true,
    "other": "عکس اُس کا مرے آئینۂ ادراک میں ہے"
  },
  {
    "line": "عالمِ نَو ہے ابھی پردۂ تقدیر میں",
    "start": 18,
    "end": 22,
    "line_number": 127,
    "file": 317,
    "first": true,
    "other": "میری نگاہوں میں ہے اس کی سحَر بےحجاب"
  },
  {
    "line": "پردہ اُٹھا دوں اگر چہرۂ افکار سے",
    "start": 0,
    "end": 4,
    "line_number": 129,
    "file": 317,
    "first": true,
    "other": "لا نہ سکے گا فرنگ میری نواؤں کی تاب"
  },
  {
    "line": "حُسنِ اَزل کی ہے نمود، چاک ہے پردۂ وجود",
    "start": 30,
    "end": 34,
    "line_number": 8,
    "file": 329,
    "first": true,
    "other": "دل کے لیے ہزار سُود ایک نگاہ کا زیاں"
  },
  {
    "line": "جہاں چھُپ گیا پردۂ رنگ میں",
    "start": 14,
    "end": 18,
    "line_number": 7,
    "file": 340,
    "first": true,
    "other": "لہُو کی ہے گردش رگِ سنگ میں"
  },
  {
    "line": "پِلا دے مجھے وہ میء پردہ سوز",
    "start": 20,
    "end": 24,
    "line_number": 19,
    "file": 340,
    "first": true,
    "other": "کہ آتی نہیں فصلِ گُل روز روز"
  },
  {
    "line": "اُٹھا ساقیا پردہ اس راز سے",
    "start": 12,
    "end": 16,
    "line_number": 25,
    "file": 340,
    "first": true,
    "other": "لڑا دے ممولے کو شہباز سے"
  },
  {
    "line": "ہے سِرِّ سرا پردۂ جاں نکتۂ معراج",
    "start": 13,
    "end": 17,
    "line_number": 8,
    "file": 394,
    "first": false,
    "other": "ناوک ہے مسلماں، ہدَف اس کا ہے ثُریّا"
  },
  {
    "line": "پردہ",
    "start": 0,
    "end": 4,
    "line_number": 1,
    "file": 490,
    "first": false,
    "other": ""
  },
  {
    "line": "نے پردہ، نہ تعلیم، نئی ہو کہ پُرانی",
    "start": 3,
    "end": 7,
    "line_number": 5,
    "file": 494,
    "first": true,
    "other": "نِسوانیَتِ زن کا نِگہباں ہے فقط مرد"
  },
  {
    "line": "خاکِ چمن اچھّی کہ سرا پردۂ افلاک!",
    "start": 22,
    "end": 26,
    "line_number": 9,
    "file": 514,
    "first": false,
    "other": "دونوں سے کِیا ہے تجھے تقدیر نے محرم"
  },
  {
    "line": "گُلشن بھی ہے اک سِرِّ سرا پردۂ افلاک",
    "start": 26,
    "end": 30,
    "line_number": 13,
    "file": 514,
    "first": false,
    "other": "کھینچیں نہ اگر تجھ کو چمن کے خس و خاشاک"
  },
  {
    "line": "ہے پردہ شگاف اُس کا اِدراک",
    "start": 3,
    "end": 7,
    "line_number": 5,
    "file": 520,
    "first": true,
    "other": "پردے ہیں تمام چاک در چاک"
  },
  {
    "line": "پردۂ تہذیب میں غارت گری، آدم کُشی",
    "start": 0,
    "end": 4,
    "line_number": 15,
    "file": 562,
    "first": true,
    "other": "کل رَوا رکھّی تھی تم نے، مَیں رَوا رکھتا ہوں آج!"
  },
  {
    "line": "ہو اگر قُوّتِ فرعون کی در پردہ مُرید",
    "start": 26,
    "end": 30,
    "line_number": 7,
    "file": 572,
    "first": true,
    "other": "قوم کے حق میں ہے لعنت وہ کِلیم اللّٰہی!"
  },
  {
    "line": "یہ مِہر ہے بےمہریِ صّیاد کا پردہ",
    "start": 28,
    "end": 32,
    "line_number": 3,
    "file": 576,
    "first": true,
    "other": "آئی نہ مرے کام مری تازہ صفیری"
  },
  {
    "line": "خورشید! سرا پردۂ مشرق سے نکل کر",
    "start": 12,
    "end": 16,
    "line_number": 11,
    "file": 593,
    "first": true,
    "other": "پہنا مرے کُہسار کو ملبوسِ حنائی"
  },
  {
    "line": "جو ملوکیّت کا اک پردہ ہو، کیا اُس سے خطر!",
    "start": 17,
    "end": 21,
    "line_number": 39,
    "file": 598,
    "first": false,
    "other": "ہُوں، مگر میری جہاں بینی بتاتی ہے مجھے"
  },
  {
    "line": "کیا بتاؤں کیا ہے کافر کی نگاہِ پردہ سوز",
    "start": 31,
    "end": 35,
    "line_number": 54,
    "file": 598,
    "first": true,
    "other": "مشرق و مغرب کی قوموں کے لیے روزِ حساب!"
  },
  {
    "line": "تیری مَیّت سے زمیں کا پردۂ نامُوس چاک",
    "start": 22,
    "end": 26,
    "line_number": 32,
    "file": 601,
    "first": false,
    "other": "تیری مَیّت سے مری تاریکیاں تاریک تر"
  }
]