[
  {
    "before": "زادۂ بحر ہوں،",
    "word": "پروردۂ",
    "after": "خورشید ہوں میں",
    "line": 22,
    "file": 5,
    "first": false,
    "other": "سبزۂ مزرعِ نوخیز کی امّید ہوں میں"
  },
  {
    "before": "اے دُرِ تابندہ، اے",
    "word": "پروَردۂ",
    "after": "آغوشِ موج!",
    "line": 34,
    "file": 117,
    "first": true,
    "other": "لذّتِ طوفاں سے ہے ناآشنا دریا ترا"
  },
  {
    "before": "گرمیِ مہر کی",
    "word": "پروَردہ",
    "after": "ہلالی دنیا",
    "line": 243,
    "file": 121,
    "first": true,
    "other": "عشق والے جسے کہتے ہیں بِلالی دنیا"
  }
]