[
  {
    "line": "اُس ولایت میں بھی ہے انساں کا دل مجبُور کیا؟",
    "start": 4,
    "end": 9,
    "line_number": 23,
    "file": 13,
    "first": false,
    "other": "آدمی واں بھی حصارِ غم میں ہے محصُور کیا؟"
  },
  {
    "line": "علمِ انساں اُس ولایت میں بھی کیا محدود ہے؟",
    "start": 15,
    "end": 20,
    "line_number": 48,
    "file": 13,
    "first": false,
    "other": "اضطرابِ دل کا ساماں یاں کی ہست و بود ہے"
  },
  {
    "line": "مَیں وہ چھوٹی سی دنیا ہوں کہ آپ اپنی ولایت ہوں",
    "start": 37,
    "end": 42,
    "line_number": 31,
    "file": 34,
    "first": false,
    "other": "نظر میری نہیں ممنونِ سیرِ عرصۂ ہستی"
  },
  {
    "line": "ولایت، پادشاہی، علمِ اشیا کی جہاں‌گیری",
    "start": 0,
    "end": 5,
    "line_number": 75,
    "file": 163,
    "first": true,
    "other": "یہ سب کیا ہیں، فقط اک نکتۂ ایماں کی تفسیریں"
  }
]