[
  {
    "line": "تَوسنِ ادراکِ انساں کو خرام آموز ہے",
    "start": 7,
    "end": 13,
    "line_number": 29,
    "file": 2,
    "first": false,
    "other": "یہ تلاشِ متصّل شمعِ جہاں افروز ہے"
  },
  {
    "line": "دُور ہو جاتی ہے ادراک کی خامی جس سے",
    "start": 16,
    "end": 21,
    "line_number": 12,
    "file": 80,
    "first": true,
    "other": "عقل کرتی ہے تاثّر کی غلامی جس سے"
  },
  {
    "line": "اے کہ نظمِ دہر کا ادراک ہے حاصل تجھے",
    "start": 18,
    "end": 23,
    "line_number": 31,
    "file": 100,
    "first": true,
    "other": "کیوں نہ آساں ہو غم و اندوہ کی منزل تجھے"
  },
  {
    "line": "غافل! تُو نِرا صاحبِ ادراک نہیں ہے",
    "start": 21,
    "end": 26,
    "line_number": 7,
    "file": 241,
    "first": false,
    "other": "ہے ذوقِ تجلّی بھی اسی خاک میں پنہاں"
  },
  {
    "line": "سمجھے گا نہ تُو جب تک بےرنگ نہ ہو ادراک",
    "start": 34,
    "end": 39,
    "line_number": 10,
    "file": 249,
    "first": false,
    "other": "کھویا گیا جو مطلب ہفتاد و دو ملّت میں"
  },
  {
    "line": "حدِ ادراک سے باہر ہیں باتیں عشق و مستی کی",
    "start": 4,
    "end": 9,
    "line_number": 12,
    "file": 269,
    "first": true,
    "other": "سمجھ میں اس قدر آیا کہ دل کی موت ہے، دُوری"
  },
  {
    "line": "عکس اُس کا مرے آئینۂ ادراک میں ہے",
    "start": 21,
    "end": 26,
    "line_number": 4,
    "file": 275,
    "first": false,
    "other": "حادثہ وہ جو ابھی پردۂ افلاک میں ہے"
  },
  {
    "line": "کسے خبر کہ جُنوں بھی ہے صاحبِ ادراک",
    "start": 30,
    "end": 35,
    "line_number": 19,
    "file": 277,
    "first": false,
    "other": "زمانہ عقل کو سمجھا ہُوا ہے مشعلِ راہ"
  },
  {
    "line": "وہ خاک کہ ہے جس کا جُنوں صَیقلِ ادراک",
    "start": 32,
    "end": 37,
    "line_number": 6,
    "file": 280,
    "first": true,
    "other": "وہ خاک کہ جبریل کی ہے جس سے قبا چاک"
  },
  {
    "line": "سَرِّ دیں ادراک میں آتا نہیں",
    "start": 10,
    "end": 15,
    "line_number": 140,
    "file": 345,
    "first": true,
    "other": "کس طرح آئے قیامت کا یقیں؟"
  },
  {
    "line": "وہ مے کہ جس سے روشن ہو ادراک",
    "start": 23,
    "end": 28,
    "line_number": 14,
    "file": 511,
    "first": false,
    "other": "رکھتا ہے اب تک مَیخانۂ شرق"
  },
  {
    "line": "ہے پردہ شگاف اُس کا اِدراک",
    "start": 20,
    "end": 26,
    "line_number": 5,
    "file": 520,
    "first": true,
    "other": "پردے ہیں تمام چاک در چاک"
  },
  {
    "line": "ترے نصیب فلاطُوں کی تیزیِ ادراک",
    "start": 26,
    "end": 31,
    "line_number": 4,
    "file": 524,
    "first": false,
    "other": "مرے لیے ہے فقط زورِ حیدری کافی"
  },
  {
    "line": "خریدتے ہیں فقط اُن کا جوہرِ ادراک!",
    "start": 28,
    "end": 33,
    "line_number": 10,
    "file": 546,
    "first": false,
    "other": "شریکِ حُکم غلاموں کو کر نہیں سکتے"
  },
  {
    "line": "کھویا گیا کس طرح ترا جوہرِ ادراک!",
    "start": 27,
    "end": 32,
    "line_number": 4,
    "file": 605,
    "first": false,
    "other": "آتی ہے دمِ صبح صدا عرشِ بریں سے"
  }
]