[
  {
    "line": "جس پہ سیمائے اُفق نازاں ہو وہ زیور ہے تو",
    "start": 13,
    "end": 17,
    "line_number": 6,
    "file": 20,
    "first": false,
    "other": "ہو دُرِ گوشِ عروسِ صبح وہ گوہر ہے تو"
  },
  {
    "line": "بدلیاں لال سی آتی ہیں اُفق پر جو نظر",
    "start": 22,
    "end": 26,
    "line_number": 14,
    "file": 25,
    "first": false,
    "other": "ہے ترے خیمۂ گردُوں کی طِلائی جھالر"
  },
  {
    "line": "اُٹھ کہ ظلمت ہوئی پیدا اُفقِ خاور پر",
    "start": 23,
    "end": 28,
    "line_number": 3,
    "file": 85,
    "first": true,
    "other": "بزم میں شعلہ نوائی سے اُجالا کر دیں"
  },
  {
    "line": "ہو رہی ہے زیرِ دامانِ اُفُق سے آشکار",
    "start": 22,
    "end": 27,
    "line_number": 3,
    "file": 98,
    "first": true,
    "other": "صبح یعنی دخترِ دوشیزۂ لیل و نہار"
  },
  {
    "line": "طشتِ اُفُق سے لے کر لالے کے پھُول مارے",
    "start": 5,
    "end": 10,
    "line_number": 4,
    "file": 109,
    "first": false,
    "other": "سُورج نے جاتے جاتے شامِ سیہ قبا کو"
  },
  {
    "line": "دیکھ کر تجھ کو اُفُق پر ہم لُٹاتے تھے گُہر",
    "start": 15,
    "end": 20,
    "line_number": 20,
    "file": 116,
    "first": true,
    "other": "اے تہی ساغر! ہماری آج ناداری بھی دیکھ"
  },
  {
    "line": "مثلِ انجم اُفُقِ قوم پہ روشن بھی ہوئے",
    "start": 10,
    "end": 16,
    "line_number": 157,
    "file": 121,
    "first": true,
    "other": "بُت ہندی کی محبت میں بَرہمن بھی ہوئے"
  },
  {
    "line": "یہ نِکلتے ہوئے سُورج کی اُفُق تابی ہے",
    "start": 24,
    "end": 29,
    "line_number": 183,
    "file": 121,
    "first": false,
    "other": "رنگ گردُوں کا ذرا دیکھ تو عُنّابی ہے"
  },
  {
    "line": "وہ چمک اُٹھّا اُفُق، گرمِ تقاضا تُو بھی ہو",
    "start": 14,
    "end": 19,
    "line_number": 10,
    "file": 126,
    "first": false,
    "other": "مسلمِ خوابیدہ اُٹھ، ہنگامہ آرا تُو بھی ہو"
  },
  {
    "line": "اُفُق سے آفتاب اُبھرا، گیا دورِ گراں خوابی",
    "start": 0,
    "end": 5,
    "line_number": 4,
    "file": 163,
    "first": false,
    "other": "دلیلِ صُبحِ روشن ہے ستاروں کی تنک تابی"
  },
  {
    "line": "اس کی زمیں بےحدود، اس کا اُفُق بےثُغور",
    "start": 25,
    "end": 30,
    "line_number": 62,
    "file": 317,
    "first": true,
    "other": "اس کے سمندر کی موج، دجلہ و دنیوب و نیل"
  },
  {
    "line": "شفَق نہیں مغربی اُفق پر یہ جُوئے خوں ہے، یہ جوئے خوں ہے!",
    "start": 16,
    "end": 20,
    "line_number": 13,
    "file": 341,
    "first": true,
    "other": "طلوعِ فردا کا منتظر رہ کہ دوش و امروز ہے فسانہ"
  }
]