[
  {
    "line": "مہینے وصل کے گھڑیوں کی صورت اُڑتے جاتے ہیں",
    "start": 34,
    "end": 38,
    "line_number": 15,
    "file": 58,
    "first": true,
    "other": "مگر گھڑیاں جُدائی کی گزرتی ہیں مہینوں میں"
  },
  {
    "line": "کہ جن کو ڈوبنا ہو، ڈوب جاتے ہیں سفینوں میں",
    "start": 23,
    "end": 27,
    "line_number": 19,
    "file": 58,
    "first": false,
    "other": "مجھے روکے گا تُو اے ناخدا کیا غرق ہونے سے"
  },
  {
    "line": "ٹل نہ سکتے تھے اگر جنگ میں اَڑ جاتے تھے",
    "start": 31,
    "end": 35,
    "line_number": 52,
    "file": 106,
    "first": true,
    "other": "پاؤں شیروں کے بھی میداں سے اُکھڑ جاتے تھے"
  },
  {
    "line": "پاؤں شیروں کے بھی میداں سے اُکھڑ جاتے تھے",
    "start": 33,
    "end": 37,
    "line_number": 53,
    "file": 106,
    "first": false,
    "other": "ٹل نہ سکتے تھے اگر جنگ میں اَڑ جاتے تھے"
  },
  {
    "line": "تجھ سے سرکش ہُوا کوئی تو بگڑ جاتے تھے",
    "start": 29,
    "end": 33,
    "line_number": 54,
    "file": 106,
    "first": true,
    "other": "تیغ کیا چیز ہے، ہم توپ سے لڑ جاتے تھے"
  },
  {
    "line": "تیغ کیا چیز ہے، ہم توپ سے لڑ جاتے تھے",
    "start": 29,
    "end": 33,
    "line_number": 55,
    "file": 106,
    "first": false,
    "other": "تجھ سے سرکش ہُوا کوئی تو بگڑ جاتے تھے"
  },
  {
    "line": "عُزلتِ شب میں مرے اشک ٹپک جاتے ہیں",
    "start": 26,
    "end": 30,
    "line_number": 23,
    "file": 108,
    "first": false,
    "other": "دن کی شورش میں نکلتے ہوئے گھبراتے ہیں"
  },
  {
    "line": "سُورج نے جاتے جاتے شامِ سیہ قبا کو",
    "start": 9,
    "end": 13,
    "line_number": 3,
    "file": 109,
    "first": true,
    "other": "طشتِ اُفُق سے لے کر لالے کے پھُول مارے"
  },
  {
    "line": "سُورج نے جاتے جاتے شامِ سیہ قبا کو",
    "start": 14,
    "end": 18,
    "line_number": 3,
    "file": 109,
    "first": true,
    "other": "طشتِ اُفُق سے لے کر لالے کے پھُول مارے"
  },
  {
    "line": "جو بادہ کش تھے پُرانے، وہ اُٹھتے جاتے ہیں",
    "start": 33,
    "end": 37,
    "line_number": 6,
    "file": 122,
    "first": true,
    "other": "کہیں سے آبِ بقائے دوام لے ساقی!"
  },
  {
    "line": "صُحبتِ مادر میں طفلِ سادہ رہ جاتے ہیں ہم",
    "start": 29,
    "end": 33,
    "line_number": 43,
    "file": 140,
    "first": false,
    "other": "زندگی کی اَوج‌گاہوں سے اُتر آتے ہیں ہم"
  },
  {
    "line": "ڈُوب جاتے ہیں سفینے موج کی آغوش میں",
    "start": 5,
    "end": 9,
    "line_number": 75,
    "file": 140,
    "first": false,
    "other": "موت ہے ہنگامہ آرا قُلزُمِ خاموش میں"
  },
  {
    "line": "دلِ آگاہ جب خوابیدہ ہو جاتے ہیں سینوں میں",
    "start": 23,
    "end": 27,
    "line_number": 15,
    "file": 149,
    "first": true,
    "other": "نوا گر کے لیے زہراب ہوتی ہے شکرخائی"
  },
  {
    "line": "مشرق میں اصول دین بن جاتے ہیں",
    "start": 21,
    "end": 25,
    "line_number": 3,
    "file": 172,
    "first": true,
    "other": "مغرب میں مگر مشین بن جاتے ہیں"
  },
  {
    "line": "مغرب میں مگر مشین بن جاتے ہیں",
    "start": 21,
    "end": 25,
    "line_number": 4,
    "file": 172,
    "first": false,
    "other": "مشرق میں اصول دین بن جاتے ہیں"
  },
  {
    "line": "واں ایک کے تین تین بن جاتے ہیں",
    "start": 22,
    "end": 26,
    "line_number": 7,
    "file": 172,
    "first": false,
    "other": "رہتا نہیں ایک بھی ہمارے پلّے"
  },
  {
    "line": "عروجِ آدمِ خاکی سے انجم سہمے جاتے ہیں",
    "start": 29,
    "end": 33,
    "line_number": 18,
    "file": 211,
    "first": true,
    "other": "کہ یہ ٹُوٹا ہوا تارا مہِ کامل نہ بن جائے"
  },
  {
    "line": "ہو جاتے ہیں سب دفتر غرقِ مئے ناب آخر",
    "start": 3,
    "end": 7,
    "line_number": 16,
    "file": 260,
    "first": false,
    "other": "کیا دبدبۂ نادر، کیا شوکتِ تیموری"
  },
  {
    "line": "کھُلے جاتے ہیں اسرارِ نہانی",
    "start": 6,
    "end": 10,
    "line_number": 3,
    "file": 322,
    "first": true,
    "other": "گیا دَورِ حدیثِ ’لن ترانی‘"
  },
  {
    "line": "جوشِ کردار سے کھُل جاتے ہیں تقدیر کے راز",
    "start": 19,
    "end": 23,
    "line_number": 4,
    "file": 356,
    "first": false,
    "other": "راز ہے، راز ہے تقدیرِ جہانِ تگ و تاز"
  },
  {
    "line": "کس درجہ بدل جاتے ہیں مُرغانِ سحَر خیز!",
    "start": 12,
    "end": 16,
    "line_number": 8,
    "file": 441,
    "first": false,
    "other": "شاہِیں کی ادا ہوتی ہے بُلبل میں نمودار"
  },
  {
    "line": "ہو جاتے ہیں افکار پراگندہ و ابتر",
    "start": 3,
    "end": 7,
    "line_number": 6,
    "file": 491,
    "first": false,
    "other": "بڑھ جاتا ہے جب ذوقِ نظر اپنی حدوں سے"
  },
  {
    "line": "کھُلتے جاتے ہیں اسی آگ سے اَسرارِ حیات",
    "start": 7,
    "end": 11,
    "line_number": 7,
    "file": 496,
    "first": true,
    "other": "گرم اسی آگ سے ہے معرکۂ بود و نبود"
  },
  {
    "line": "پُختہ ہو جاتے ہیں جب خُوئے غلامی میں غلام!",
    "start": 9,
    "end": 13,
    "line_number": 8,
    "file": 553,
    "first": false,
    "other": "خواجگی میں کوئی مشکل نہیں رہتی باقی"
  }
]