[
  {
    "line": "“نمیگردید کوتہ رشتۂ معنی رہا کردم",
    "start": 29,
    "end": 33,
    "line_number": 146,
    "file": 34,
    "first": true,
    "other": "حکایت بود بےپایاں، بخاموشی ادا کردم”"
  },
  {
    "line": "حکایت بود بےپایاں، بخاموشی ادا کردم”",
    "start": 31,
    "end": 35,
    "line_number": 147,
    "file": 34,
    "first": false,
    "other": "“نمیگردید کوتہ رشتۂ معنی رہا کردم"
  },
  {
    "line": "منم کہ توبہ نہ کردم ز فاش گوئی ہا",
    "start": 15,
    "end": 19,
    "line_number": 11,
    "file": 634,
    "first": true,
    "other": "ز بیمِ ایں کہ بسُلطاں کنند غمّازی"
  }
]