[
  {
    "line": "نکلا کبھی گہن سے، آیا کبھی گہن میں",
    "start": 0,
    "end": 4,
    "line_number": 14,
    "file": 40,
    "first": false,
    "other": "چھوٹے سے چاند میں ہے ظلمت بھی روشنی بھی"
  },
  {
    "line": "چمن کو چھوڑ کے نِکلا ہوں مثلِ نکہتِ گُل",
    "start": 15,
    "end": 20,
    "line_number": 14,
    "file": 49,
    "first": true,
    "other": "ہُوا ہے صبر کا منظور امتحاں مجھ کو"
  },
  {
    "line": "مکاں نکلا ہمارے خانۂ دل کے مکینوں میں",
    "start": 5,
    "end": 9,
    "line_number": 7,
    "file": 58,
    "first": false,
    "other": "حقیقت اپنی آنکھوں پر نمایاں جب ہوئی اپنی"
  },
  {
    "line": "حلقۂ صُبح و شام سے نکلا",
    "start": 19,
    "end": 23,
    "line_number": 9,
    "file": 110,
    "first": true,
    "other": "اس پُرانے نظام سے نکلا"
  },
  {
    "line": "اس پُرانے نظام سے نکلا",
    "start": 18,
    "end": 22,
    "line_number": 10,
    "file": 110,
    "first": false,
    "other": "حلقۂ صُبح و شام سے نکلا"
  },
  {
    "line": "کہ المانی سے بھی پائندہ تر نکلا ہے تُورانی",
    "start": 27,
    "end": 31,
    "line_number": 67,
    "file": 163,
    "first": false,
    "other": "ثباتِ زندگی ایمانِ مُحکم سے ہے دنیا میں"
  }
]