[
  {
    "before": "لُطفِ صد حاصل ہماری",
    "word": "سعیِ",
    "after": "بےحاصل میں ہے",
    "line": 48,
    "file": 20,
    "first": false,
    "other": "کس قدر لذّت کشودِ عقدۂ مشکل میں ہے"
  },
  {
    "before": "تمنّائے دلی آخر بر آئی",
    "word": "سعیِ",
    "after": "پیہم سے",
    "line": 25,
    "file": 63,
    "first": false,
    "other": "بڑھا تسبیح خوانی کے بہانے عرش کی جانب"
  },
  {
    "before": "",
    "word": "سعیِ",
    "after": "پیہم ہے ترازُوئے کم و کیفِ حیات",
    "line": 21,
    "file": 166,
    "first": true,
    "other": "تیری میزاں ہے شمارِ سحَر و شام ابھی"
  },
  {
    "before": "یہ ہماری",
    "word": "سعیِ",
    "after": "پیہم کی کرامت ہے کہ آج",
    "line": 24,
    "file": 598,
    "first": true,
    "other": "صوفی و مُلّا مُلوکیّت کے بندے ہیں تمام"
  }
]