[
  {
    "line": "یہ جگر سوزی چراغِ خانۂ حکمت نہ ہو",
    "start": 7,
    "end": 11,
    "line_number": 25,
    "file": 2,
    "first": false,
    "other": "یہ پریشانی مری سامانِ جمعیّت نہ ہو"
  },
  {
    "line": "کیا جہنّم معصیت سوزی کی اک ترکیب ہے؟",
    "start": 16,
    "end": 20,
    "line_number": 43,
    "file": 13,
    "first": true,
    "other": "آگ کے شعلوں میں پنہاں مقصدِ تادیب ہے؟"
  },
  {
    "line": "برقِ دیرینہ کو فرمانِ جگر سوزی دے",
    "start": 26,
    "end": 30,
    "line_number": 176,
    "file": 106,
    "first": false,
    "other": "اپنے پروانوں کو پھر ذوقِ خُود افروزی دے"
  },
  {
    "line": "وہ جگر سوزی نہیں، وہ شعلہ آشامی نہیں",
    "start": 7,
    "end": 11,
    "line_number": 58,
    "file": 117,
    "first": true,
    "other": "فائدہ پھر کیا جو گِردِ شمع پروانے رہے"
  },
  {
    "line": "مری تقدیر ہے خاشاک سوزی",
    "start": 19,
    "end": 23,
    "line_number": 5,
    "file": 308,
    "first": true,
    "other": "فقط بجلی ہوں مَیں، حاصل نہیں مَیں"
  },
  {
    "line": "خاموشی و دل سوزی، سرمستی و رعنائی!",
    "start": 12,
    "end": 16,
    "line_number": 18,
    "file": 338,
    "first": false,
    "other": "اے بادِ بیابانی! مجھ کو بھی عنایت ہو"
  }
]