[
  {
    "line": "تُو جواں ہے گردشِ شام و سحَر کے درمیاں",
    "start": 12,
    "end": 17,
    "line_number": 6,
    "file": 1,
    "first": false,
    "other": "تجھ میں کُچھ پیدا نہیں دیرینہ روزی کے نشاں"
  },
  {
    "line": "دوڑ پیچھے کی طرف اے گردشِ ایّام تُو",
    "start": 20,
    "end": 25,
    "line_number": 57,
    "file": 1,
    "first": false,
    "other": "ہاں دکھا دے اے تصوّر پھر وہ صبح و شام تُو"
  },
  {
    "line": "چھُپا جس میں علاجِ گردشِ چرخِ کُہن بھی ہے",
    "start": 19,
    "end": 24,
    "line_number": 137,
    "file": 34,
    "first": false,
    "other": "مرَض کہتے ہیں سب اس کو، یہ ہے لیکن مرَض ایسا"
  },
  {
    "line": "میری گردش بھی مثالِ گردشِ پَرکار ہے",
    "start": 5,
    "end": 9,
    "line_number": 16,
    "file": 36,
    "first": false,
    "other": "ایک حلقے پر اگر قائم تری رفتار ہے"
  },
  {
    "line": "میری گردش بھی مثالِ گردشِ پَرکار ہے",
    "start": 20,
    "end": 25,
    "line_number": 16,
    "file": 36,
    "first": false,
    "other": "ایک حلقے پر اگر قائم تری رفتار ہے"
  },
  {
    "line": "سِکھایا مسئلۂ گردشِ زمیں میں نے",
    "start": 14,
    "end": 19,
    "line_number": 43,
    "file": 38,
    "first": false,
    "other": "ڈرا سکِیں نہ کلیسا کی مجھ کو تلواریں"
  },
  {
    "line": "نہ تھا واقف ابھی گردش کے آئینِ مسلّم سے",
    "start": 17,
    "end": 21,
    "line_number": 7,
    "file": 63,
    "first": false,
    "other": "قمر اپنے لباسِ نَو میں بیگانہ سا لگتا تھا"
  },
  {
    "line": "گردشِ آدمی ہے اور، گردشِ جام اور ہے",
    "start": 0,
    "end": 5,
    "line_number": 16,
    "file": 67,
    "first": false,
    "other": "موت ہے عیشِ جاوداں، ذوقِ طلب اگر نہ ہو"
  },
  {
    "line": "گردشِ آدمی ہے اور، گردشِ جام اور ہے",
    "start": 19,
    "end": 24,
    "line_number": 16,
    "file": 67,
    "first": false,
    "other": "موت ہے عیشِ جاوداں، ذوقِ طلب اگر نہ ہو"
  },
  {
    "line": "گردش تاروں کا ہے مقدّر",
    "start": 0,
    "end": 4,
    "line_number": 12,
    "file": 96,
    "first": true,
    "other": "ہر ایک کی راہ ہے مقرّر"
  },
  {
    "line": "کل تلک گردش میں جس ساقی کے پیمانے رہے",
    "start": 7,
    "end": 11,
    "line_number": 63,
    "file": 117,
    "first": false,
    "other": "رو رہی ہے آج اک ٹوٹی ہُوئی مِینا اُسے"
  },
  {
    "line": "پُختہ تر ہے گردشِ پیہم سے جامِ زندگی",
    "start": 12,
    "end": 17,
    "line_number": 52,
    "file": 162,
    "first": true,
    "other": "ہے یہی اے بےخبر رازِ دوامِ زندگی"
  },
  {
    "line": "دِگرگُوں ہے جہاں، تاروں کی گردش تیز ہے ساقی",
    "start": 27,
    "end": 31,
    "line_number": 3,
    "file": 213,
    "first": true,
    "other": "دل ہر ذرّہ میں غوغائے رستاخیز ہے ساقی"
  },
  {
    "line": "تری نگاہ کی گردش ہے میری رستاخیز",
    "start": 12,
    "end": 16,
    "line_number": 13,
    "file": 223,
    "first": false,
    "other": "کسے خبر ہے کہ ہنگامۂ نشور ہے کیا"
  },
  {
    "line": "یا مَیں نہیں، یا گردشِ افلاک نہیں ہے",
    "start": 17,
    "end": 22,
    "line_number": 16,
    "file": 241,
    "first": false,
    "other": "کب تک رہے محکومیِ انجم میں مری خاک"
  },
  {
    "line": "نہ ہے ستارے کی گردش، نہ بازیِ افلاک",
    "start": 15,
    "end": 19,
    "line_number": 18,
    "file": 254,
    "first": true,
    "other": "خودی کی موت ہے تیرا زوالِ نعمت و جاہ"
  },
  {
    "line": "رگوں میں گردشِ خُوں ہے اگر تو کیا حاصل",
    "start": 9,
    "end": 14,
    "line_number": 12,
    "file": 255,
    "first": true,
    "other": "حیات سوزِ جگر کے سوا کچھ اور نہیں"
  },
  {
    "line": "اعجاز ہے کسی کا یا گردشِ زمانہ!",
    "start": 19,
    "end": 24,
    "line_number": 3,
    "file": 263,
    "first": true,
    "other": "ٹُوٹا ہے ایشیا میں سِحرِ فرنگیانہ"
  },
  {
    "line": "نہ ستارے میں ہے، نَے گردشِ افلاک میں ہے",
    "start": 21,
    "end": 26,
    "line_number": 6,
    "file": 275,
    "first": true,
    "other": "تیری تقدیر مرے نالۂ بےباک میں ہے"
  },
  {
    "line": "گردشِ دَوراں کا ہے جس کی زباں پر گِلہ",
    "start": 0,
    "end": 5,
    "line_number": 13,
    "file": 284,
    "first": false,
    "other": "اُس کی خودی ہے ابھی شام و سحَر میں اسیر"
  },
  {
    "line": "غلامِ گردشِ دوراں نہیں دل",
    "start": 6,
    "end": 11,
    "line_number": 6,
    "file": 301,
    "first": false,
    "other": "اسیرِ دوش و فردا ہے و لیکن"
  },
  {
    "line": "تیرے جہاں میں ہے وہی گردشِ صُبح و شام ابھی",
    "start": 21,
    "end": 26,
    "line_number": 6,
    "file": 326,
    "first": false,
    "other": "خلقِ خدا کی گھات میں رِند و فقیہ و مِیر و پیر"
  },
  {
    "line": "تِیرہ و تار ہے جہاں گردشِ آفتاب سے",
    "start": 20,
    "end": 25,
    "line_number": 55,
    "file": 329,
    "first": true,
    "other": "طبعِ زمانہ تازہ کر جلوۂ بےحجاب سے"
  },
  {
    "line": "لہُو کی ہے گردش رگِ سنگ میں",
    "start": 11,
    "end": 15,
    "line_number": 8,
    "file": 340,
    "first": false,
    "other": "جہاں چھُپ گیا پردۂ رنگ میں"
  },
  {
    "line": "وہی جام گردش میں لا ساقیا!",
    "start": 8,
    "end": 12,
    "line_number": 58,
    "file": 340,
    "first": false,
    "other": "شرابِ کُہن پھر پِلا ساقیا"
  },
  {
    "line": "یہ ہے مقصدِ گردشِ روزگار",
    "start": 12,
    "end": 17,
    "line_number": 197,
    "file": 340,
    "first": true,
    "other": "کہ تیری خودی تجھ پہ ہو آشکار"
  },
  {
    "line": "وہی زمانے کی گردش پہ غالب آتا ہے",
    "start": 13,
    "end": 17,
    "line_number": 7,
    "file": 499,
    "first": true,
    "other": "جو ہر نفَس سے کرے عُمرِ جاوداں پیدا"
  },
  {
    "line": "تیشے کی کوئی گردشِ تقدیر تو دیکھے",
    "start": 13,
    "end": 18,
    "line_number": 9,
    "file": 603,
    "first": true,
    "other": "سیراب ہے پرویز، جِگر تَشنہ ہے فرہاد"
  },
  {
    "line": "فقط اک گردشِ شام و سحر ہے",
    "start": 7,
    "end": 12,
    "line_number": 5,
    "file": 618,
    "first": true,
    "other": "اگر دیکھیں فروغِ مہر و مہ سے"
  },
  {
    "line": "گردش مہ و ستارہ کی ہے ناگوار اسے",
    "start": 0,
    "end": 4,
    "line_number": 5,
    "file": 628,
    "first": true,
    "other": "دل آپ اپنے شام و سحَر کا ہے نقش بند"
  }
]